mp4/mipspipe_mp4.v
// Incomplete behavioral model of MIPS pipeline
// Code your design here
module mipspipe_mp4 (clock);
  
// in_out
  input clock;

  // Instruction opcodes
  parameter LW = 6'b100011, SW = 6'b101011, BEQ = 6'b000100, nop = 32'b00000_100000, ALUop = 6'b0;
  reg [31:0] PC, Regs[0:31], IMemory[0:1023], DMemory[0:1023], // instruction and data memories
             IFIDIR, IDEXA, IDEXB, IDEXIR, EXMEMIR, EXMEMB, // pipeline latches
             EXMEMALUOut, MEMWBValue, MEMWBIR;

  wire [4:0] IDEXrs, IDEXrt, EXMEMrd, MEMWBrd; //hold register fields
  wire [5:0] EXMEMop, MEMWBop, IDEXop; //Hold opcodes
  wire [31:0] Ain, Bin;
  // declare the bypass signals
  wire takebranch, stall, bypassAfromMEM,     bypassAfromALUinWB,bypassBfromMEM, bypassBfromALUinWB,
  bypassAfromLWinWB, bypassBfromLWinWB;
  
  assign IDEXrs = IDEXIR[25:21]; // rs field
  assign IDEXrt = IDEXIR[20:16]; // rt field
  assign EXMEMrd = EXMEMIR[15:11]; // rd field
  assign MEMWBrd = MEMWBIR[15:11]; // rd field
  assign MEMWBrt = MEMWBIR[20:16]; // rt field -- for loads
  assign EXMEMop = EXMEMIR[31:26]; // opcode
  assign MEMWBop = MEMWBIR[31:26]; // opcode
  assign IDEXop = IDEXIR[31:26]; // opcode
 /*
 assign IDEXrs = IDEXIR[25:21];
 assign IDEXrt = IDEXIR[15:11]; 
 assign EXMEMrd = EXMEMIR[15:11];
 assign MEMWBrd = MEMWBIR[20:16]; 
 assign EXMEMop = EXMEMIR[31:26];
 assign MEMWBop = MEMWBIR[31:26]; 
 assign IDEXop = IDEXIR[31:26];
 */
  
 // The bypass to input A from the MEM stage for an ALU operation
 assign bypassAfromMEM = (IDEXrs == EXMEMrd) & (IDEXrs!=0) & (EXMEMop==ALUop); // yes, bypass
 // The bypass to input B from the MEM stage for an ALU operation
 assign bypassBfromMEM = (IDEXrt == EXMEMrd)&(IDEXrt!=0) & (EXMEMop==ALUop); // yes, bypass
 // The bypass to input A from the WB stage for an ALU operation
 assign bypassAfromALUinWB =( IDEXrs == MEMWBrd) & (IDEXrs!=0) & (MEMWBop==ALUop);
 // The bypass to input B from the WB stage for an ALU operation
 assign bypassBfromALUinWB = (IDEXrt == MEMWBrd) & (IDEXrt!=0) & (MEMWBop==ALUop); 
 // The bypass to input A from the WB stage for an LW operation
 assign bypassAfromLWinWB =( IDEXrs == MEMWBIR[20:16]) & (IDEXrs!=0) & (MEMWBop==LW);
 // The bypass to input B from the WB stage for an LW operation
 assign bypassBfromLWinWB = (IDEXrt == MEMWBIR[20:16]) & (IDEXrt!=0) & (MEMWBop==LW);
 // The A input to the ALU is bypassed from MEM if there is a bypass there,
 // Otherwise from WB if there is a bypass there, and otherwise comes from the IDEX register
 assign Ain = bypassAfromMEM? EXMEMALUOut :
 (bypassAfromALUinWB | bypassAfromLWinWB)? MEMWBValue : IDEXA;
 // The B input to the ALU is bypassed from MEM if there is a bypass there,
 // Otherwise from WB if there is a bypass there, and otherwise comes from the IDEX register
 assign Bin = bypassBfromMEM? EXMEMALUOut :
 (bypassBfromALUinWB | bypassBfromLWinWB)? MEMWBValue: IDEXB;
 // The signal for detecting a stall based on the use of a result from LW
 //assign stall = 0;
  assign stall = (MEMWBIR[31:26]==LW) && // source instruction is a load
 ((((IDEXop==LW)|(IDEXop==SW)) && (IDEXrs==MEMWBrd)) | // stall for address calc
((IDEXop==ALUop) && ((IDEXrs==MEMWBrd)|(IDEXrt==MEMWBrd)))); // ALU use
// Signal for a taken branch: instruction is BEQ and registers are equal
 assign takebranch = (IFIDIR[31:26]==BEQ) && (Regs[IFIDIR[25:21]]== Regs[IFIDIR[20:16]]);
  
 reg [5:0] i; //used to initialize registers
 reg [10:0] j,k; // used to initialize memories
 
 initial begin
 PC = 0;
 IFIDIR = nop; 
 IDEXIR = nop;
 EXMEMIR = nop;
 MEMWBIR = nop; // put no-ops in pipeline registers
  for (i = 0;i<=31;i = i+1) Regs[i] = i; //initialize registers--just so they aren’t don’t cares
    IMemory[0] = 32'h8ca30002;
    IMemory[1] = 32'h8c620007;
    IMemory[2] = 32'h10200003;    
    IMemory[3] = 32'h8c0b0010;
    IMemory[4] = 32'had6f0009;
    IMemory[5] = 32'h10210001;
    IMemory[6] = 32'h8ca30002;  
    IMemory[7] = 32'h8c0b0010;
    IMemory[8] = 32'h002b6020;
  for (j=9; j<=1023; j=j+1) IMemory[j] = nop; // initialize instruction memories
    
    DMemory[0] = 32'h00000000;
    DMemory[1] = 32'h0000000d;
    DMemory[2] = 32'h00000000;
    DMemory[3] = 32'h00000000;
    DMemory[4] = 32'h00000003;
    DMemory[5] = 32'hffffffff;
  for (k=6; k<=1023; k=k+1) DMemory[k] = 0; //
 end
 
 always @ (posedge clock) 
 begin
 if (~stall) begin // the first three pipeline stages stall if there is a load hazard
 if (~takebranch) begin // first instruction in the pipeline is being fetched normally
 IFIDIR <= IMemory[PC>>2];
 PC <= PC + 4;
 end else begin // a taken branch is in ID; instruction in IF is wrong; insert a no-op and reset the PC
 IFIDIR <= nop;
 PC <= PC + ({{16{IFIDIR[15]}}, IFIDIR[15:0]}<<2);
 end


 /*  
   
 // second instruction is in register fetch
 IDEXA <= Regs[IFIDIR[25:21]]; 
 IDEXB <= Regs[IFIDIR[20:16]]; // get two registers
 // third instruction is doing address calculation or ALU operation
 IDEXIR <= IFIDIR; //pass along IR

 if ((IDEXop==LW) |(IDEXop==SW)) // address calculation & copy B
 EXMEMALUOut <= IDEXA +{{16{IDEXIR[15]}}, IDEXIR[15:0]};
 else if (IDEXop==ALUop) case (IDEXIR[5:0]) //case for the various R-type instructions
 32: EXMEMALUOut <= Ain + Bin; //add operation
 default: ; //other R-type operations: subtract, SLT, etc.
 endcase
 EXMEMIR <= IDEXIR; EXMEMB <= IDEXB; //pass along the IR & B register
 end
 else EXMEMIR <= nop; //Freeze first three stages of pipeline; inject a nop into the EX output

//*/
  //*
      // DECODE: Read registers
      if (~takebranch)
      begin 
        IDEXA <= Regs[IFIDIR[25:21]];
        IDEXB <= Regs[IFIDIR[20:16]];
        IDEXIR <= IFIDIR;
      end
      else
      begin // a taken branch is in EX; instruction in ID is wrong; insert a nop
        IDEXIR <= nop;
      end
    end  // end of if(~stall) block
    else IDEXIR <= nop; // Freeze first two stages of pipeline if stalled for load hazard

    // EX: Address calculation or ALU operation
    if ((IDEXop==LW) |(IDEXop==SW)) // address calculation & copy B
      EXMEMALUOut <= Ain +{{16{IDEXIR[15]}}, IDEXIR[15:0]};
    else if (IDEXop==ALUop)
    begin
      case (IDEXIR[5:0]) // R-type instruction
        32: EXMEMALUOut <= Ain + Bin; // add operation
        default: ; // other R-type operations: subtract, SLT, etc.
      endcase
    end
   
    EXMEMIR <= IDEXIR;
    EXMEMB <= Bin; // pass along the IR & B register
//*/


 //Mem stage of pipeline
 if (EXMEMop==ALUop) MEMWBValue <= EXMEMALUOut; //pass along ALU result
 else if (EXMEMop == LW) MEMWBValue <= DMemory[EXMEMALUOut>>2];
 else if (EXMEMop == SW) DMemory[EXMEMALUOut>>2] <=EXMEMB; //store
 // the WB stage
 MEMWBIR <= EXMEMIR; //pass along IR
 if ((MEMWBop==ALUop) & (MEMWBrd != 0)) Regs[MEMWBrd] <= MEMWBValue; // ALU operation
 else if ((EXMEMop == LW)& (MEMWBIR[20:16] != 0)) Regs[MEMWBIR[20:16]] <= MEMWBValue;
 end
endmodule

mp4/testbench.sv
//
// Test bench for the mipspipe
// Boram Leejavascript:void(0)
//
  
`include "mipspipe_mp4.v"
  
module test_mipspipe;
  
  reg clock;
  reg [3:0] clock_cycle;

// instantiate pipeline module
  mipspipe_mp4 u_mipspipe_mp4(clock);
 
// initialize clock and cycle counter 
  initial begin
    clock = 0;
    clock_cycle=4'h0;
    #160  $finish;
  end
  
// 10 unit clock cycle
  always 
    #5 clock = ~clock;

  always @(posedge clock)
     begin
       clock_cycle=clock_cycle+1;
     end


// display contents of pipeline latches at the end of each clock cycle
  always @(negedge clock) 
     begin
     $display("\n\nclock cycle = %d",clock_cycle," (time = %1.0t)",$time);
     $display("IF/ID registers\n\t IF/ID.PC+4 = %h, IF/ID.IR = %h \n", u_mipspipe_mp4.PC, u_mipspipe_mp4.IFIDIR); 
     $display("ID/EX registers\n\t ID/EX.rs = %d, ID/EX.rt = %d",u_mipspipe_mp4.IDEXrs,u_mipspipe_mp4.IDEXrt,"\n\t ID/EX.A = %h, ID/EX.B = %h",u_mipspipe_mp4.IDEXA,u_mipspipe_mp4.IDEXB);
     $display("\t ID/EX.op = %h\n",u_mipspipe_mp4.IDEXop);
     $display("EX/MEM registers\n\t EX/MEM.rs = %d, EX/MEM.rt = %d",u_mipspipe_mp4.IDEXrs,u_mipspipe_mp4.IDEXrt,"\n\t EX/MEM.ALUOut = %h, EX/MEM.ALUout = %h",u_mipspipe_mp4.EXMEMALUOut,u_mipspipe_mp4.EXMEMB);
     $display("\t EX/MEM.op = %h\n",u_mipspipe_mp4.EXMEMop);
     $display("MEM/WB registers\n\t MEM/WB.rd = %d, MEM/WB.rt = %d",u_mipspipe_mp4.MEMWBrd,u_mipspipe_mp4.MEMWBrt,"\n\t MEM/WB.value = %h",u_mipspipe_mp4.MEMWBValue);
     $display("\t EX/MEM.op = %h\n",u_mipspipe_mp4.MEMWBop);
     end
      
// log to a vcd (variable change dump) file
   initial
      begin
      $dumpfile("test_mipspipe.vcd");
      $dumpvars;
   end

endmodule

mp4/test_mipspipe.vcd
$date
	Fri Apr 24 04:04:18 2020
$end
$version
	Icarus Verilog
$end
$timescale
	1s
$end
$scope module test_mipspipe $end
$var reg 1 ! clock $end
$var reg 4 " clock_cycle [3:0] $end
$scope module u_mipspipe_mp4 $end
$var wire 1 # bypassAfromALUinWB $end
$var wire 1 $ bypassAfromLWinWB $end
$var wire 1 % bypassAfromMEM $end
$var wire 1 & bypassBfromALUinWB $end
$var wire 1 ' bypassBfromLWinWB $end
$var wire 1 ( bypassBfromMEM $end
$var wire 1 ! clock $end
$var wire 1 ) stall $end
$var wire 1 * takebranch $end
$var wire 1 + MEMWBrt $end
$var wire 5 , MEMWBrd [4:0] $end
$var wire 6 - MEMWBop [5:0] $end
$var wire 5 . IDEXrt [4:0] $end
$var wire 5 / IDEXrs [4:0] $end
$var wire 6 0 IDEXop [5:0] $end
$var wire 5 1 EXMEMrd [4:0] $end
$var wire 6 2 EXMEMop [5:0] $end
$var wire 32 3 Bin [31:0] $end
$var wire 32 4 Ain [31:0] $end
$var reg 32 5 EXMEMALUOut [31:0] $end
$var reg 32 6 EXMEMB [31:0] $end
$var reg 32 7 EXMEMIR [31:0] $end
$var reg 32 8 IDEXA [31:0] $end
$var reg 32 9 IDEXB [31:0] $end
$var reg 32 : IDEXIR [31:0] $end
$var reg 32 ; IFIDIR [31:0] $end
$var reg 32 < MEMWBIR [31:0] $end
$var reg 32 = MEMWBValue [31:0] $end
$var reg 32 > PC [31:0] $end
$var reg 6 ? i [5:0] $end
$var reg 11 @ j [10:0] $end
$var reg 11 A k [10:0] $end
$upscope $end
$upscope $end
$enddefinitions $end
#0
$dumpvars
b10000000000 A
b10000000000 @
b100000 ?
b0 >
bx =
b100000 <
b100000 ;
b100000 :
bx 9
bx 8
b100000 7
bx 6
bx 5
bx 4
bx 3
b0 2
b0 1
b0 0
b0 /
b0 .
b0 -
b0 ,
0+
0*
0)
0(
0'
0&
0%
0$
0#
b0 "
0!
$end
#5
b0 3
b0 4
b0 9
b0 8
b100 >
b10001100101000110000000000000010 ;
b1 "
1!
#10
0!
#15
b11 3
b101 4
b101 /
b11 .
b100011 0
b0 6
b0 5
b10001100101000110000000000000010 :
b11 9
b101 8
b1000 >
b10001100011000100000000000000111 ;
b10 "
1!
#20
0!
#25
b10 3
b11 4
b100011 2
b11 /
b10 .
b0 =
b11 6
b10001100101000110000000000000010 7
b111 5
b10001100011000100000000000000111 :
b10 9
b11 8
b1100 >
b10000001000000000000000000011 ;
b11 "
1!
#30
0!
#35
1+
b0 3
b1 4
b100011 -
b1 /
b0 .
b100 0
b10001100101000110000000000000010 <
b1101 =
b10 6
b10001100011000100000000000000111 7
b1010 5
b10000001000000000000000000011 :
b0 9
b1 8
b10000 >
b10001100000010110000000000010000 ;
b100 "
1!
#40
0!
#45
1)
0+
b1011 3
b0 4
b100 2
b0 /
b1011 .
b100011 0
b10001100011000100000000000000111 <
b0 =
b0 6
b10000001000000000000000000011 7
b10001100000010110000000000010000 :
b1011 9
b0 8
b10100 >
b10101101011011110000000000001001 ;
b101 "
1!
#50
0!
#55
0)
b100 -
b100011 2
b0 .
b0 0
b10000001000000000000000000011 <
b1011 6
b10001100000010110000000000010000 7
b10000 5
b100000 :
b110 "
1!
#60
0!
#65
1+
1$
0)
b1111 3
b11 4
1*
b100011 -
b0 2
b1011 /
b1111 .
b101011 0
b10001100000010110000000000010000 <
b11 =
b100000 7
b1011 5
b10101101011011110000000000001001 :
b1111 9
b1011 8
b11000 >
b10000001000010000000000000001 ;
b111 "
1!
#70
0!
#75
0+
0$
b1011 4
0*
b0 -
b101011 2
b0 /
b0 .
b0 0
b100000 <
b1011 =
b1111 6
b10101101011011110000000000001001 7
b1100 5
b100000 :
b11100 >
b100000 ;
b1000 "
1!
#80
0!
#85
1+
b0 3
b0 4
b101011 -
b0 2
b10101101011011110000000000001001 <
b100000 7
b11010 5
b0 9
b0 8
b100000 >
b10001100000010110000000000010000 ;
b1001 "
1!
#90
0!
#95
0+
b1011 3
b0 -
b1011 .
b100011 0
b100000 <
b11010 =
b0 6
b0 5
b10001100000010110000000000010000 :
b1011 9
b100100 >
b1010110110000000100000 ;
b1010 "
1!
#100
0!
#105
b1 4
b100011 2
b1 /
b0 0
b0 =
b1011 6
b10001100000010110000000000010000 7
b10000 5
b1010110110000000100000 :
b1 8
b101000 >
b100000 ;
b1011 "
1!
#110
0!
#115
1)
1+
b0 3
b0 4
b100011 -
b1100 1
b0 2
b0 /
b0 .
b10001100000010110000000000010000 <
b11 =
b1010110110000000100000 7
b1100 5
b100000 :
b0 9
b0 8
b101100 >
b1100 "
1!
#120
0!
#125
0)
b1100 ,
b0 -
b0 1
b1010110110000000100000 <
b1100 =
b0 6
b100000 7
b0 5
b1101 "
1!
#130
0!
#135
0+
b0 ,
b100000 <
b0 =
b110000 >
b1110 "
1!
#140
0!
#145
b110100 >
b1111 "
1!
#150
0!
#155
b111000 >
b0 "
1!
